{
  "hash": "e9e42c1d",
  "configHash": "d991c691",
  "lockfileHash": "6aed19cd",
  "browserHash": "8092e1f3",
  "optimized": {
    "react": {
      "src": "../../node_modules/react/index.js",
      "file": "react.js",
      "fileHash": "421f2e38",
      "needsInterop": true
    },
    "react-router-dom": {
      "src": "../../node_modules/react-router-dom/dist/index.mjs",
      "file": "react-router-dom.js",
      "fileHash": "02a2801a",
      "needsInterop": false
    },
    "axios": {
      "src": "../../node_modules/axios/index.js",
      "file": "axios.js",
      "fileHash": "4f773dee",
      "needsInterop": false
    },
    "@supabase/supabase-js": {
      "src": "../../node_modules/@supabase/supabase-js/dist/index.mjs",
      "file": "@supabase_supabase-js.js",
      "fileHash": "46471a09",
      "needsInterop": false
    },
    "react-dom/client": {
      "src": "../../node_modules/react-dom/client.js",
      "file": "react-dom_client.js",
      "fileHash": "e4955276",
      "needsInterop": true
    }
  },
  "chunks": {
    "chunk-AU2MKR2E": {
      "file": "chunk-AU2MKR2E.js"
    },
    "chunk-VX2H6PUQ": {
      "file": "chunk-VX2H6PUQ.js"
    },
    "chunk-G3PMV62Z": {
      "file": "chunk-G3PMV62Z.js"
    }
  }
}